{
  "content": {
    "transcript": "Stop all the clocks. Cut off the telephone. Prevent the dog from barking with a juicy bone. Silence the pianos and with muffled drum bring out the coffin. Let the mourners come. Let aeroplanes circle moaning overhead, dead, scribbling on the sky the message, he is dead. Put crepe bows round the white necks of the public doves. Let the traffic policemen wear black cotton gloves. He was my north, my south, my east and west, my working week and my Sunday rest, my noon. My midnight, my talk, my song. I thought that love would last forever. I was wrong. The stars are not wanted now. Put out everyone. Pack up the moon and dismantle the sun. Pour away the ocean and sweep up the wood. For nothing lasts forever. Nothing now can ever come to any good.",
    "segments": [
      { "start_time": 0.0, "end_time": 1.4, "text": "Stop all the clocks." },
      { "start_time": 3.2, "end_time": 4.8, "text": "Cut off the telephone." },
      { "start_time": 7.52, "end_time": 10.6, "text": "Prevent the dog from barking with a juicy bone." },
      { "start_time": 12.9, "end_time": 15.84, "text": "Silence the pianos and with muffled drum" },
      { "start_time": 15.84, "end_time": 17.74, "text": "bring out the coffin." },
      { "start_time": 19.34, "end_time": 20.72, "text": "Let the mourners come." },
      { "start_time": 23.26, "end_time": 26.64, "text": "Let aeroplanes circle moaning overhead," },
      { "start_time": 26.64, "end_time": 30.18, "text": "dead, scribbling on the sky the message," },
      { "start_time": 31.88, "end_time": 32.48, "text": "he is dead." },
      { "start_time": 34.72, "end_time": 37.84, "text": "Put crepe bows round the white necks of the public doves." },
      { "start_time": 39.44, "end_time": 42.68, "text": "Let the traffic policemen wear black cotton gloves." },
      { "start_time": 46.08, "end_time": 50.72, "text": "He was my north, my south, my east and west," },
      { "start_time": 51.9, "end_time": 54.28, "text": "my working week and my Sunday rest," },
      { "start_time": 55.46, "end_time": 56.54, "text": "my noon." },
      { "start_time": 56.64, "end_time": 59.64, "text": "My midnight, my talk, my song." },
      { "start_time": 63.04, "end_time": 65.2, "text": "I thought that love would last forever." },
      { "start_time": 66.36, "end_time": 67.2, "text": "I was wrong." },
      { "start_time": 69.32, "end_time": 71.04, "text": "The stars are not wanted now." },
      { "start_time": 72.08, "end_time": 73.8, "text": "Put out everyone." },
      { "start_time": 76.36, "end_time": 79.16, "text": "Pack up the moon and dismantle the sun." },
      { "start_time": 81.04, "end_time": 83.4, "text": "Pour away the ocean and sweep up the wood." },
      { "start_time": 85.24, "end_time": 86.64, "text": "For nothing lasts forever." },
      { "start_time": 86.64, "end_time": 89.64, "text": "Nothing now can ever come to any good." }
    ],
    "word_timestamps": [
      { "word": "Stop", "start_time": 0.0, "end_time": 0.35 },
      { "word": "all", "start_time": 0.35, "end_time": 0.7 },
      { "word": "the", "start_time": 0.7, "end_time": 1.0499999999999998 },
      { "word": "clocks.", "start_time": 1.0499999999999998, "end_time": 1.4 },
      { "word": "Cut", "start_time": 3.2, "end_time": 3.6 },
      { "word": "off", "start_time": 3.6, "end_time": 4.0 },
      { "word": "the", "start_time": 4.0, "end_time": 4.4 },
      { "word": "telephone.", "start_time": 4.4, "end_time": 4.800000000000001 },
      { "word": "Prevent", "start_time": 7.52, "end_time": 7.862222222222222 },
      { "word": "the", "start_time": 7.862222222222222, "end_time": 8.204444444444444 },
      { "word": "dog", "start_time": 8.204444444444444, "end_time": 8.546666666666667 },
      { "word": "from", "start_time": 8.546666666666667, "end_time": 8.88888888888889 },
      { "word": "barking", "start_time": 8.88888888888889, "end_time": 9.231111111111112 },
      { "word": "with", "start_time": 9.231111111111112, "end_time": 9.573333333333334 },
      { "word": "a", "start_time": 9.573333333333334, "end_time": 9.915555555555557 },
      { "word": "juicy", "start_time": 9.915555555555557, "end_time": 10.257777777777779 },
      { "word": "bone.", "start_time": 10.257777777777779, "end_time": 10.600000000000001 },
      { "word": "Silence", "start_time": 12.9, "end_time": 13.32 },
      { "word": "the", "start_time": 13.32, "end_time": 13.74 },
      { "word": "pianos", "start_time": 13.74, "end_time": 14.16 },
      { "word": "and", "start_time": 14.16, "end_time": 14.58 },
      { "word": "with", "start_time": 14.58, "end_time": 15.0 },
      { "word": "muffled", "start_time": 15.0, "end_time": 15.42 },
      { "word": "drum", "start_time": 15.42, "end_time": 15.84 },
      { "word": "bring", "start_time": 15.84, "end_time": 16.314999999999998 },
      { "word": "out", "start_time": 16.314999999999998, "end_time": 16.79 },
      { "word": "the", "start_time": 16.79, "end_time": 17.265 },
      { "word": "coffin.", "start_time": 17.265, "end_time": 17.740000000000002 },
      { "word": "Let", "start_time": 19.34, "end_time": 19.685 },
      { "word": "the", "start_time": 19.685, "end_time": 20.029999999999998 },
      { "word": "mourners", "start_time": 20.029999999999998, "end_time": 20.374999999999996 },
      { "word": "come.", "start_time": 20.374999999999996, "end_time": 20.719999999999995 },
      { "word": "Let", "start_time": 23.26, "end_time": 23.936 },
      { "word": "aeroplanes", "start_time": 23.936, "end_time": 24.612 },
      { "word": "circle", "start_time": 24.612, "end_time": 25.287999999999997 },
      { "word": "moaning", "start_time": 25.287999999999997, "end_time": 25.963999999999995 },
      { "word": "overhead,", "start_time": 25.963999999999995, "end_time": 26.639999999999993 },
      { "word": "dead,", "start_time": 26.64, "end_time": 27.145714285714288 },
      { "word": "scribbling", "start_time": 27.145714285714288, "end_time": 27.651428571428575 },
      { "word": "on", "start_time": 27.651428571428575, "end_time": 28.157142857142862 },
      { "word": "the", "start_time": 28.157142857142862, "end_time": 28.66285714285715 },
      { "word": "sky", "start_time": 28.66285714285715, "end_time": 29.168571428571436 },
      { "word": "the", "start_time": 29.168571428571436, "end_time": 29.674285714285723 },
      { "word": "message,", "start_time": 29.674285714285723, "end_time": 30.18000000000001 },
      { "word": "he", "start_time": 31.88, "end_time": 32.08 },
      { "word": "is", "start_time": 32.08, "end_time": 32.28 },
      { "word": "dead.", "start_time": 32.28, "end_time": 32.480000000000004 },
      { "word": "Put", "start_time": 34.72, "end_time": 35.00363636363636 },
      { "word": "crepe", "start_time": 35.00363636363636, "end_time": 35.28727272727272 },
      { "word": "bows", "start_time": 35.28727272727272, "end_time": 35.57090909090908 },
      { "word": "round", "start_time": 35.57090909090908, "end_time": 35.854545454545445 },
      { "word": "the", "start_time": 35.854545454545445, "end_time": 36.138181818181806 },
      { "word": "white", "start_time": 36.138181818181806, "end_time": 36.42181818181817 },
      { "word": "necks", "start_time": 36.42181818181817, "end_time": 36.70545454545453 },
      { "word": "of", "start_time": 36.70545454545453, "end_time": 36.98909090909089 },
      { "word": "the", "start_time": 36.98909090909089, "end_time": 37.27272727272725 },
      { "word": "public", "start_time": 37.27272727272725, "end_time": 37.55636363636361 },
      { "word": "doves.", "start_time": 37.55636363636361, "end_time": 37.839999999999975 },
      { "word": "Let", "start_time": 39.44, "end_time": 39.845 },
      { "word": "the", "start_time": 39.845, "end_time": 40.25 },
      { "word": "traffic", "start_time": 40.25, "end_time": 40.655 },
      { "word": "policemen", "start_time": 40.655, "end_time": 41.06 },
      { "word": "wear", "start_time": 41.06, "end_time": 41.465 },
      { "word": "black", "start_time": 41.465, "end_time": 41.870000000000005 },
      { "word": "cotton", "start_time": 41.870000000000005, "end_time": 42.275000000000006 },
      { "word": "gloves.", "start_time": 42.275000000000006, "end_time": 42.68000000000001 },
      { "word": "He", "start_time": 46.08, "end_time": 46.544 },
      { "word": "was", "start_time": 46.544, "end_time": 47.007999999999996 },
      { "word": "my", "start_time": 47.007999999999996, "end_time": 47.471999999999994 },
      { "word": "north,", "start_time": 47.471999999999994, "end_time": 47.93599999999999 },
      { "word": "my", "start_time": 47.93599999999999, "end_time": 48.39999999999999 },
      { "word": "south,", "start_time": 48.39999999999999, "end_time": 48.86399999999999 },
      { "word": "my", "start_time": 48.86399999999999, "end_time": 49.32799999999999 },
      { "word": "east", "start_time": 49.32799999999999, "end_time": 49.79199999999999 },
      { "word": "and", "start_time": 49.79199999999999, "end_time": 50.255999999999986 },
      { "word": "west,", "start_time": 50.255999999999986, "end_time": 50.719999999999985 },
      { "word": "my", "start_time": 51.9, "end_time": 52.24 },
      { "word": "working", "start_time": 52.24, "end_time": 52.580000000000005 },
      { "word": "week", "start_time": 52.580000000000005, "end_time": 52.92000000000001 },
      { "word": "and", "start_time": 52.92000000000001, "end_time": 53.26000000000001 },
      { "word": "my", "start_time": 53.26000000000001, "end_time": 53.600000000000016 },
      { "word": "Sunday", "start_time": 53.600000000000016, "end_time": 53.94000000000002 },
      { "word": "rest,", "start_time": 53.94000000000002, "end_time": 54.28000000000002 },
      { "word": "my", "start_time": 55.46, "end_time": 56.0 },
      { "word": "noon.", "start_time": 56.0, "end_time": 56.54 },
      { "word": "My", "start_time": 56.64, "end_time": 57.14 },
      { "word": "midnight,", "start_time": 57.14, "end_time": 57.64 },
      { "word": "my", "start_time": 57.64, "end_time": 58.14 },
      { "word": "talk,", "start_time": 58.14, "end_time": 58.64 },
      { "word": "my", "start_time": 58.64, "end_time": 59.14 },
      { "word": "song.", "start_time": 59.14, "end_time": 59.64 },
      { "word": "I", "start_time": 63.04, "end_time": 63.348571428571425 },
      { "word": "thought", "start_time": 63.348571428571425, "end_time": 63.65714285714285 },
      { "word": "that", "start_time": 63.65714285714285, "end_time": 63.96571428571428 },
      { "word": "love", "start_time": 63.96571428571428, "end_time": 64.27428571428571 },
      { "word": "would", "start_time": 64.27428571428571, "end_time": 64.58285714285714 },
      { "word": "last", "start_time": 64.58285714285714, "end_time": 64.89142857142856 },
      { "word": "forever.", "start_time": 64.89142857142856, "end_time": 65.19999999999999 },
      { "word": "I", "start_time": 66.36, "end_time": 66.64 },
      { "word": "was", "start_time": 66.64, "end_time": 66.92 },
      { "word": "wrong.", "start_time": 66.92, "end_time": 67.2 },
      { "word": "The", "start_time": 69.32, "end_time": 69.60666666666665 },
      { "word": "stars", "start_time": 69.60666666666665, "end_time": 69.89333333333332 },
      { "word": "are", "start_time": 69.89333333333332, "end_time": 70.17999999999998 },
      { "word": "not", "start_time": 70.17999999999998, "end_time": 70.46666666666664 },
      { "word": "wanted", "start_time": 70.46666666666664, "end_time": 70.7533333333333 },
      { "word": "now.", "start_time": 70.7533333333333, "end_time": 71.03999999999996 },
      { "word": "Put", "start_time": 72.08, "end_time": 72.65333333333334 },
      { "word": "out", "start_time": 72.65333333333334, "end_time": 73.22666666666667 },
      { "word": "everyone.", "start_time": 73.22666666666667, "end_time": 73.80000000000001 },
      { "word": "Pack", "start_time": 76.36, "end_time": 76.71 },
      { "word": "up", "start_time": 76.71, "end_time": 77.05999999999999 },
      { "word": "the", "start_time": 77.05999999999999, "end_time": 77.40999999999998 },
      { "word": "moon", "start_time": 77.40999999999998, "end_time": 77.75999999999998 },
      { "word": "and", "start_time": 77.75999999999998, "end_time": 78.10999999999997 },
      { "word": "dismantle", "start_time": 78.10999999999997, "end_time": 78.45999999999997 },
      { "word": "the", "start_time": 78.45999999999997, "end_time": 78.80999999999996 },
      { "word": "sun.", "start_time": 78.80999999999996, "end_time": 79.15999999999995 },
      { "word": "Pour", "start_time": 81.04, "end_time": 81.30222222222223 },
      { "word": "away", "start_time": 81.30222222222223, "end_time": 81.56444444444445 },
      { "word": "the", "start_time": 81.56444444444445, "end_time": 81.82666666666667 },
      { "word": "ocean", "start_time": 81.82666666666667, "end_time": 82.08888888888889 },
      { "word": "and", "start_time": 82.08888888888889, "end_time": 82.35111111111111 },
      { "word": "sweep", "start_time": 82.35111111111111, "end_time": 82.61333333333333 },
      { "word": "up", "start_time": 82.61333333333333, "end_time": 82.87555555555555 },
      { "word": "the", "start_time": 82.87555555555555, "end_time": 83.13777777777777 },
      { "word": "wood.", "start_time": 83.13777777777777, "end_time": 83.39999999999999 },
      { "word": "For", "start_time": 85.24, "end_time": 85.59 },
      { "word": "nothing", "start_time": 85.59, "end_time": 85.94 },
      { "word": "lasts", "start_time": 85.94, "end_time": 86.28999999999999 },
      { "word": "forever.", "start_time": 86.28999999999999, "end_time": 86.63999999999999 },
      { "word": "Nothing", "start_time": 86.64, "end_time": 87.015 },
      { "word": "now", "start_time": 87.015, "end_time": 87.39 },
      { "word": "can", "start_time": 87.39, "end_time": 87.765 },
      { "word": "ever", "start_time": 87.765, "end_time": 88.14 },
      { "word": "come", "start_time": 88.14, "end_time": 88.515 },
      { "word": "to", "start_time": 88.515, "end_time": 88.89 },
      { "word": "any", "start_time": 88.89, "end_time": 89.265 },
      { "word": "good.", "start_time": 89.265, "end_time": 89.64 }
    ]
  }
}
